multiversx_sdk_network_providers/__init__.py
multiversx_sdk_network_providers/accounts.py
multiversx_sdk_network_providers/api_network_provider.py
multiversx_sdk_network_providers/api_network_provider_test.py
multiversx_sdk_network_providers/config.py
multiversx_sdk_network_providers/constants.py
multiversx_sdk_network_providers/contract_query_requests.py
multiversx_sdk_network_providers/contract_query_response.py
multiversx_sdk_network_providers/contract_results.py
multiversx_sdk_network_providers/errors.py
multiversx_sdk_network_providers/interface.py
multiversx_sdk_network_providers/network_config.py
multiversx_sdk_network_providers/network_general_statistics.py
multiversx_sdk_network_providers/network_stake.py
multiversx_sdk_network_providers/network_status.py
multiversx_sdk_network_providers/proxy_network_provider.py
multiversx_sdk_network_providers/proxy_network_provider_test.py
multiversx_sdk_network_providers/resources.py
multiversx_sdk_network_providers/token_definitions.py
multiversx_sdk_network_providers/tokens.py
multiversx_sdk_network_providers/transaction_events.py
multiversx_sdk_network_providers/transaction_logs.py
multiversx_sdk_network_providers/transaction_receipt.py
multiversx_sdk_network_providers/transaction_status.py
multiversx_sdk_network_providers/transactions.py
multiversx_sdk_network_providers/utils.py
multiversx_sdk_network_providers-0.13.0.dist-info/METADATA
multiversx_sdk_network_providers-0.13.0.dist-info/WHEEL
multiversx_sdk_network_providers-0.13.0.dist-info/licenses/LICENSE
multiversx_sdk_network_providers-0.13.0.dist-info/RECORD
