Metadata-Version: 2.1
Name: multiversx-sdk-network-providers
Version: 0.13.0
Summary: Network providers for MultiversX Python SDK.
Project-URL: Homepage, https://github.com/multiversx/mx-sdk-py-network-providers
Author: MultiversX
License-Expression: MIT
License-File: LICENSE
Classifier: License :: OSI Approved :: MIT License
Classifier: Operating System :: OS Independent
Classifier: Programming Language :: Python :: 3
Requires-Python: >=3.8
Requires-Dist: multiversx-sdk-core<0.9.0,>=0.8.0
Requires-Dist: requests==2.31.0
